mopidy_bigscreen/__init__.py
mopidy_bigscreen/ext.conf
mopidy_bigscreen/static/asset-manifest.json
mopidy_bigscreen/static/fish.webp
mopidy_bigscreen/static/index.html
mopidy_bigscreen/static/static/css/main.0140e641.css
mopidy_bigscreen/static/static/css/main.0140e641.css.map
mopidy_bigscreen/static/static/js/main.94f28e7e.js
mopidy_bigscreen/static/static/js/main.94f28e7e.js.LICENSE.txt
mopidy_bigscreen/static/static/js/main.94f28e7e.js.map
Mopidy_BigScreen-0.1.0.dist-info/LICENSE
Mopidy_BigScreen-0.1.0.dist-info/METADATA
Mopidy_BigScreen-0.1.0.dist-info/WHEEL
Mopidy_BigScreen-0.1.0.dist-info/entry_points.txt
Mopidy_BigScreen-0.1.0.dist-info/top_level.txt
Mopidy_BigScreen-0.1.0.dist-info/RECORD
